{
    "name":"ROBERT F RAKOWSKI",
    "gender":"man",
    "gender_color":"blue",
    "researcharea":"physics",
    "researcharea_color":"#573470",
    "children":[
        {
            "name":"SANDEEP  SAGAR",
            "gender":"man",
            "gender_color":"blue",
            "researcharea":"physics",
            "researcharea_color":"#573470"
        },
        {
            "name":"ALEKSANDR  VASILYEV",
            "gender":"man",
            "gender_color":"blue",
            "researcharea":"physics",
            "researcharea_color":"#573470"
        }
    ]
}