{
    "name":"DONALD W BRENNER",
    "gender":"man",
    "gender_color":"blue",
    "researcharea":"physics",
    "researcharea_color":"#573470",
    "children":[
        {
            "name":"NATALIE M GIBSON",
            "gender":"woman",
            "gender_color":"red",
            "researcharea":"physics",
            "researcharea_color":"#573470"
        },
        {
            "name":"YOJNA  PUROHIT",
            "gender":"woman",
            "gender_color":"red",
            "researcharea":"physics",
            "researcharea_color":"#573470"
        },
        {
            "name":"DENIS A ARESHKIN",
            "gender":"man",
            "gender_color":"blue",
            "researcharea":"physics",
            "researcharea_color":"#573470"
        },
        {
            "name":"MARK K BEHBEHANI",
            "gender":"man",
            "gender_color":"blue",
            "researcharea":"physics",
            "researcharea_color":"#573470"
        }
    ]
}