{
    "name":"YAEL  SHADMI",
    "gender":"woman",
    "gender_color":"red",
    "researcharea":"physics",
    "researcharea_color":"#573470",
    "children":[
        {
            "name":"SUBHENDU  RAKSHIT",
            "gender":"man",
            "gender_color":"blue",
            "researcharea":"physics",
            "researcharea_color":"#573470",
            "children":[
                {
                    "name":"SUJATA  PANDEY",
                    "gender":"woman",
                    "gender_color":"red",
                    "researcharea":"physics",
                    "researcharea_color":"#573470"
                },
                {
                    "name":"SIDDHARTHA  KARMAKAR",
                    "gender":"man",
                    "gender_color":"blue",
                    "researcharea":"physics",
                    "researcharea_color":"#573470"
                }
            ]
        }
    ]
}