{
    "name":"BRADFORD  JAMESON",
    "gender":"man",
    "gender_color":"blue",
    "researcharea":"physics",
    "researcharea_color":"#573470",
    "children":[
        {
            "name":"ROSS H ALBERT",
            "gender":"man",
            "gender_color":"blue",
            "researcharea":"physics",
            "researcharea_color":"#573470"
        },
        {
            "name":"HAROLD C DAVIDSON",
            "gender":"man",
            "gender_color":"blue",
            "researcharea":"physics",
            "researcharea_color":"#573470"
        }
    ]
}