{
    "name":"MARTIN  TRUFFER",
    "gender":"man",
    "gender_color":"blue",
    "researcharea":"physics",
    "researcharea_color":"#573470",
    "children":[
        {
            "name":"MARIJKE  HABERMANN",
            "gender":"woman",
            "gender_color":"red",
            "researcharea":"physics",
            "researcharea_color":"#573470"
        },
        {
            "name":"BARBARA L TRUSSEL",
            "gender":"woman",
            "gender_color":"red",
            "researcharea":"physics",
            "researcharea_color":"#573470"
        },
        {
            "name":"JASON M AMUNDSON",
            "gender":"man",
            "gender_color":"blue",
            "researcharea":"physics",
            "researcharea_color":"#573470"
        },
        {
            "name":"DAVID B PODRASKY",
            "gender":"man",
            "gender_color":"blue",
            "researcharea":"physics",
            "researcharea_color":"#573470"
        }
    ]
}