{
    "name":"NORA  BERRAH",
    "gender":"woman",
    "gender_color":"red",
    "researcharea":"physics",
    "researcharea_color":"#573470",
    "children":[
        {
            "name":"ILEANA  DUMITRIU",
            "gender":"woman",
            "gender_color":"red",
            "researcharea":"physics",
            "researcharea_color":"#573470"
        },
        {
            "name":"SOPHIE E CANTON",
            "gender":"woman",
            "gender_color":"red",
            "researcharea":"physics",
            "researcharea_color":"#573470"
        },
        {
            "name":"MARCO  WIEDENHOEFT",
            "gender":"man",
            "gender_color":"blue",
            "researcharea":"physics",
            "researcharea_color":"#573470"
        }
    ]
}