{
    "name":"DAVID ANDREW YPHANTIS",
    "gender":"man",
    "gender_color":"blue",
    "researcharea":"physics",
    "researcharea_color":"#573470",
    "children":[
        {
            "name":"TOM  LAUE",
            "gender":"man",
            "gender_color":"blue",
            "researcharea":"physics",
            "researcharea_color":"#573470",
            "children":[
                {
                    "name":"JOHN C CHAMPAGNE",
                    "gender":"man",
                    "gender_color":"blue",
                    "researcharea":"physics",
                    "researcharea_color":"#573470"
                }
            ]
        }
    ]
}