{
    "name":"HOLLY A LAVOIE",
    "gender":"woman",
    "gender_color":"red",
    "researcharea":"physics",
    "researcharea_color":"#573470",
    "children":[
        {
            "name":"CAROLINA G MEINA",
            "gender":"woman",
            "gender_color":"red",
            "researcharea":"physics",
            "researcharea_color":"#573470"
        },
        {
            "name":"RALUCA  RUSOVICI",
            "gender":"woman",
            "gender_color":"red",
            "researcharea":"physics",
            "researcharea_color":"#573470"
        }
    ]
}