{
    "name":"SHEILA EVANS WIDNALL",
    "gender":"woman",
    "gender_color":"red",
    "researcharea":"physics",
    "researcharea_color":"#573470",
    "children":[
        {
            "name":"RAYMOND T PIERREHUMBERT",
            "gender":"man",
            "gender_color":"blue",
            "researcharea":"physics",
            "researcharea_color":"#573470",
            "children":[
                {
                    "name":"JONATHAN L MITCHELL",
                    "gender":"man",
                    "gender_color":"blue",
                    "researcharea":"physics",
                    "researcharea_color":"#573470",
                    "children":[
                        {
                            "name":"KUNIO M SAYANAGI",
                            "gender":"man",
                            "gender_color":"blue",
                            "researcharea":"physics",
                            "researcharea_color":"#573470",
                            "children":[
                                {
                                    "name":"JOHN J J BLALOCK",
                                    "gender":"man",
                                    "gender_color":"blue",
                                    "researcharea":"physics",
                                    "researcharea_color":"#573470"
                                },
                                {
                                    "name":"SHAWN R BRUESHABER",
                                    "gender":"man",
                                    "gender_color":"blue",
                                    "researcharea":"physics",
                                    "researcharea_color":"#573470"
                                },
                                {
                                    "name":"NICHOLAS G HEAVENS",
                                    "gender":"man",
                                    "gender_color":"blue",
                                    "researcharea":"physics",
                                    "researcharea_color":"#573470",
                                    "children":[
                                        {
                                            "name":"ALIMA  DIAWARA",
                                            "gender":"woman",
                                            "gender_color":"red",
                                            "researcharea":"physics",
                                            "researcharea_color":"#573470"
                                        }
                                    ]
                                },
                                {
                                    "name":"JUSTIN MICHAEL GARLAND",
                                    "gender":"man",
                                    "gender_color":"blue",
                                    "researcharea":"physics",
                                    "researcharea_color":"#573470"
                                }
                            ]
                        }
                    ]
                },
                {
                    "name":"IAN N WILLIAMS",
                    "gender":"man",
                    "gender_color":"blue",
                    "researcharea":"physics",
                    "researcharea_color":"#573470"
                }
            ]
        }
    ]
}