{
    "name":"DANA  GADDY",
    "gender":"woman",
    "gender_color":"red",
    "researcharea":"physics",
    "researcharea_color":"#573470",
    "children":[
        {
            "name":"KRISTY M NICKS",
            "gender":"woman",
            "gender_color":"red",
            "researcharea":"physics",
            "researcharea_color":"#573470"
        },
        {
            "name":"SUZANNE J BAKEWELL",
            "gender":"woman",
            "gender_color":"red",
            "researcharea":"physics",
            "researcharea_color":"#573470"
        },
        {
            "name":"DANIEL S PERRIEN",
            "gender":"man",
            "gender_color":"blue",
            "researcharea":"physics",
            "researcharea_color":"#573470"
        },
        {
            "name":"TRISTAN W FOWLER",
            "gender":"man",
            "gender_color":"blue",
            "researcharea":"physics",
            "researcharea_color":"#573470"
        }
    ]
}