{
    "name":"ALI BULENT CAMBEL",
    "gender":"man",
    "gender_color":"blue",
    "researcharea":"physics",
    "researcharea_color":"#573470",
    "children":[
        {
            "name":"THEODORE FREDERICK MORSE",
            "gender":"man",
            "gender_color":"blue",
            "researcharea":"physics",
            "researcharea_color":"#573470",
            "children":[
                {
                    "name":"FLOYD B HANSON",
                    "gender":"man",
                    "gender_color":"blue",
                    "researcharea":"physics",
                    "researcharea_color":"#573470",
                    "children":[
                        {
                            "name":"SIDDHARTHA P CHAKRABARTY",
                            "gender":"man",
                            "gender_color":"blue",
                            "researcharea":"physics",
                            "researcharea_color":"#573470"
                        },
                        {
                            "name":"HARRY  CHENG",
                            "gender":"man",
                            "gender_color":"blue",
                            "researcharea":"physics",
                            "researcharea_color":"#573470",
                            "children":[
                                {
                                    "name":"DAVID  KO",
                                    "gender":"man",
                                    "gender_color":"blue",
                                    "researcharea":"physics",
                                    "researcharea_color":"#573470"
                                },
                                {
                                    "name":"STEPHEN S NESTINGER",
                                    "gender":"man",
                                    "gender_color":"blue",
                                    "researcharea":"physics",
                                    "researcharea_color":"#573470"
                                }
                            ]
                        }
                    ]
                },
                {
                    "name":"ROMAN L SHUBOCHKIN",
                    "gender":"man",
                    "gender_color":"blue",
                    "researcharea":"physics",
                    "researcharea_color":"#573470"
                }
            ]
        }
    ]
}