{
    "name":"JOHANNES ADOLPH OVERBECK",
    "gender":"man",
    "gender_color":"blue",
    "researcharea":"hist",
    "researcharea_color":"#68A839",
    "children":[
        {
            "name":"ADOLF  MICHAELIS",
            "gender":"man",
            "gender_color":"blue",
            "researcharea":"hist",
            "researcharea_color":"#68A839"
        },
        {
            "name":"PAUL  ARNDT",
            "gender":"man",
            "gender_color":"blue",
            "researcharea":"hist",
            "researcharea_color":"#68A839"
        },
        {
            "name":"WALTHER OSKAR ERNST AMELUNG",
            "gender":"man",
            "gender_color":"blue",
            "researcharea":"hist",
            "researcharea_color":"#68A839"
        },
        {
            "name":"ADOLF  FURTWANGLER",
            "gender":"man",
            "gender_color":"blue",
            "researcharea":"hist",
            "researcharea_color":"#68A839",
            "children":[
                {
                    "name":"WILLEM  VOGELSANG",
                    "gender":"man",
                    "gender_color":"blue",
                    "researcharea":"ling",
                    "researcharea_color":"#DE12F5",
                    "children":[
                        {
                            "name":"JAN GERRIT VAN GELDER",
                            "gender":"man",
                            "gender_color":"blue",
                            "researcharea":"ling",
                            "researcharea_color":"#DE12F5",
                            "children":[
                                {
                                    "name":"JOSUA  BRUYN",
                                    "gender":"man",
                                    "gender_color":"blue",
                                    "researcharea":"hist",
                                    "researcharea_color":"#68A839"
                                }
                            ]
                        }
                    ]
                }
            ]
        }
    ]
}