{
    "name":"MARSHA  HAUFLER",
    "gender":"woman",
    "gender_color":"red",
    "researcharea":"hist",
    "researcharea_color":"#68A839",
    "children":[
        {
            "name":"NOELLE  GIUFFRIDA",
            "gender":"woman",
            "gender_color":"red",
            "researcharea":"hist",
            "researcharea_color":"#68A839"
        },
        {
            "name":"DIANNE L MORTON",
            "gender":"woman",
            "gender_color":"red",
            "researcharea":"hist",
            "researcharea_color":"#68A839"
        },
        {
            "name":"KYUNGWON  CHOE",
            "gender":"man",
            "gender_color":"blue",
            "researcharea":"hist",
            "researcharea_color":"#68A839"
        },
        {
            "name":"KEVIN R GREENWOOD",
            "gender":"man",
            "gender_color":"blue",
            "researcharea":"hist",
            "researcharea_color":"#68A839"
        }
    ]
}