{
    "name":"NICHOLAS  TEMPERLEY",
    "gender":"man",
    "gender_color":"blue",
    "researcharea":"hist",
    "researcharea_color":"#68A839",
    "children":[
        {
            "name":"ELISA F WILSON",
            "gender":"woman",
            "gender_color":"red",
            "researcharea":"hist",
            "researcharea_color":"#68A839"
        },
        {
            "name":"JOSEPH  HERL",
            "gender":"man",
            "gender_color":"blue",
            "researcharea":"hist",
            "researcharea_color":"#68A839"
        }
    ]
}