{
    "name":"DEBORAH  HARKNESS",
    "gender":"woman",
    "gender_color":"red",
    "researcharea":"hist",
    "researcharea_color":"#68A839",
    "children":[
        {
            "name":"MICHELE L CLOUSE",
            "gender":"woman",
            "gender_color":"red",
            "researcharea":"hist",
            "researcharea_color":"#68A839"
        },
        {
            "name":"CELESTE C CHAMBERLAND",
            "gender":"woman",
            "gender_color":"red",
            "researcharea":"hist",
            "researcharea_color":"#68A839"
        }
    ]
}