{
    "name":"EUGENE  LERMAN",
    "gender":"man",
    "gender_color":"blue",
    "researcharea":"math",
    "researcharea_color":"#8F3CCC",
    "children":[
        {
            "name":"CHRISTOPHER B WILLETT",
            "gender":"man",
            "gender_color":"blue",
            "researcharea":"math",
            "researcharea_color":"#8F3CCC"
        },
        {
            "name":"DANIEL  MORTON",
            "gender":"man",
            "gender_color":"blue",
            "researcharea":"math",
            "researcharea_color":"#8F3CCC"
        }
    ]
}