{
    "name":"MICHAEL J KOLEN",
    "gender":"man",
    "gender_color":"blue",
    "researcharea":"math",
    "researcharea_color":"#8F3CCC",
    "children":[
        {
            "name":"ANNA M TOPCZEWSKI",
            "gender":"woman",
            "gender_color":"red",
            "researcharea":"math",
            "researcharea_color":"#8F3CCC"
        },
        {
            "name":"KATHERINE E CASTELLANO",
            "gender":"woman",
            "gender_color":"red",
            "researcharea":"math",
            "researcharea_color":"#8F3CCC"
        },
        {
            "name":"SONYA J POWERS",
            "gender":"woman",
            "gender_color":"red",
            "researcharea":"math",
            "researcharea_color":"#8F3CCC"
        },
        {
            "name":"SARAH L HAGGE",
            "gender":"woman",
            "gender_color":"red",
            "researcharea":"math",
            "researcharea_color":"#8F3CCC"
        },
        {
            "name":"KYNDRA V MIDDLETON",
            "gender":"woman",
            "gender_color":"red",
            "researcharea":"math",
            "researcharea_color":"#8F3CCC"
        },
        {
            "name":"NOOREE  HUH",
            "gender":"woman",
            "gender_color":"red",
            "researcharea":"math",
            "researcharea_color":"#8F3CCC"
        },
        {
            "name":"AMY B HENDRICKSON",
            "gender":"woman",
            "gender_color":"red",
            "researcharea":"math",
            "researcharea_color":"#8F3CCC"
        },
        {
            "name":"RASHID S AL-MAHRAZI",
            "gender":"man",
            "gender_color":"blue",
            "researcharea":"math",
            "researcharea_color":"#8F3CCC"
        },
        {
            "name":"SEONGHOON  KIM",
            "gender":"man",
            "gender_color":"blue",
            "researcharea":"math",
            "researcharea_color":"#8F3CCC"
        },
        {
            "name":"YOUNGWOO  CHO",
            "gender":"man",
            "gender_color":"blue",
            "researcharea":"math",
            "researcharea_color":"#8F3CCC"
        },
        {
            "name":"NATHAN L WALL",
            "gender":"man",
            "gender_color":"blue",
            "researcharea":"math",
            "researcharea_color":"#8F3CCC"
        }
    ]
}