{
    "name":"GREGORY  BEYLKIN",
    "gender":"man",
    "gender_color":"blue",
    "researcharea":"math",
    "researcharea_color":"#8F3CCC",
    "children":[
        {
            "name":"KRISTIAN H SANDBERG",
            "gender":"man",
            "gender_color":"blue",
            "researcharea":"math",
            "researcharea_color":"#8F3CCC"
        },
        {
            "name":"CHRISTOPHER  KURCZ",
            "gender":"man",
            "gender_color":"blue",
            "researcharea":"math",
            "researcharea_color":"#8F3CCC"
        },
        {
            "name":"DAVID J BIAGIONI",
            "gender":"man",
            "gender_color":"blue",
            "researcharea":"math",
            "researcharea_color":"#8F3CCC"
        },
        {
            "name":"MATTHEW  REYNOLDS",
            "gender":"man",
            "gender_color":"blue",
            "researcharea":"math",
            "researcharea_color":"#8F3CCC"
        }
    ]
}