{
    "name":"ERIC P SMITH",
    "gender":"man",
    "gender_color":"blue",
    "researcharea":"math",
    "researcharea_color":"#8F3CCC",
    "children":[
        {
            "name":"KIMBERLY R LOVE",
            "gender":"woman",
            "gender_color":"red",
            "researcharea":"math",
            "researcharea_color":"#8F3CCC"
        },
        {
            "name":"ROBERT B NOBLE",
            "gender":"man",
            "gender_color":"blue",
            "researcharea":"math",
            "researcharea_color":"#8F3CCC"
        },
        {
            "name":"ILYA A LIPKOVICH",
            "gender":"man",
            "gender_color":"blue",
            "researcharea":"math",
            "researcharea_color":"#8F3CCC"
        },
        {
            "name":"DAVID B FARRAR",
            "gender":"man",
            "gender_color":"blue",
            "researcharea":"math",
            "researcharea_color":"#8F3CCC"
        },
        {
            "name":"JONATHAN W DUGGINS",
            "gender":"man",
            "gender_color":"blue",
            "researcharea":"math",
            "researcharea_color":"#8F3CCC"
        }
    ]
}