{
    "name":"PETER C SARNAK",
    "gender":"man",
    "gender_color":"blue",
    "researcharea":"math",
    "researcharea_color":"#8F3CCC",
    "children":[
        {
            "name":"ELENA  FUCHS",
            "gender":"woman",
            "gender_color":"red",
            "researcharea":"math",
            "researcharea_color":"#8F3CCC"
        },
        {
            "name":"JADE P VINSON",
            "gender":"woman",
            "gender_color":"red",
            "researcharea":"math",
            "researcharea_color":"#8F3CCC"
        },
        {
            "name":"JAY  JORGENSON",
            "gender":"man",
            "gender_color":"blue",
            "researcharea":"math",
            "researcharea_color":"#8F3CCC",
            "children":[
                {
                    "name":"DANIEL J GARBIN",
                    "gender":"man",
                    "gender_color":"blue",
                    "researcharea":"math",
                    "researcharea_color":"#8F3CCC"
                }
            ]
        },
        {
            "name":"ALEXANDRU  ZAHARESCU",
            "gender":"man",
            "gender_color":"blue",
            "researcharea":"math",
            "researcharea_color":"#8F3CCC",
            "children":[
                {
                    "name":"ANDREW H LEDOAN",
                    "gender":"man",
                    "gender_color":"blue",
                    "researcharea":"math",
                    "researcharea_color":"#8F3CCC"
                }
            ]
        },
        {
            "name":"KANNAN  SOUNDARARAJAN",
            "gender":"man",
            "gender_color":"blue",
            "researcharea":"math",
            "researcharea_color":"#8F3CCC"
        },
        {
            "name":"AKSHAY  VENKATESH",
            "gender":"man",
            "gender_color":"blue",
            "researcharea":"math",
            "researcharea_color":"#8F3CCC"
        },
        {
            "name":"ALEX  ESKIN",
            "gender":"man",
            "gender_color":"blue",
            "researcharea":"math",
            "researcharea_color":"#8F3CCC",
            "children":[
                {
                    "name":"IRINE  PENG",
                    "gender":"woman",
                    "gender_color":"red",
                    "researcharea":"math",
                    "researcharea_color":"#8F3CCC"
                },
                {
                    "name":"KARIANE  CALTA",
                    "gender":"woman",
                    "gender_color":"red",
                    "researcharea":"math",
                    "researcharea_color":"#8F3CCC"
                },
                {
                    "name":"THOMAS  ZAMOJSKI",
                    "gender":"man",
                    "gender_color":"blue",
                    "researcharea":"math",
                    "researcharea_color":"#8F3CCC"
                },
                {
                    "name":"ILYA  GEKHTMAN",
                    "gender":"man",
                    "gender_color":"blue",
                    "researcharea":"math",
                    "researcharea_color":"#8F3CCC"
                }
            ]
        },
        {
            "name":"WILLIAM  DUKE",
            "gender":"man",
            "gender_color":"blue",
            "researcharea":"math",
            "researcharea_color":"#8F3CCC",
            "children":[
                {
                    "name":"AMANDA L FOLSOM",
                    "gender":"woman",
                    "gender_color":"red",
                    "researcharea":"math",
                    "researcharea_color":"#8F3CCC"
                },
                {
                    "name":"RYAN C DAILEDA",
                    "gender":"man",
                    "gender_color":"blue",
                    "researcharea":"math",
                    "researcharea_color":"#8F3CCC"
                },
                {
                    "name":"NATHAN C JONES",
                    "gender":"man",
                    "gender_color":"blue",
                    "researcharea":"math",
                    "researcharea_color":"#8F3CCC"
                },
                {
                    "name":"JOHN G LEO",
                    "gender":"man",
                    "gender_color":"blue",
                    "researcharea":"math",
                    "researcharea_color":"#8F3CCC"
                },
                {
                    "name":"JACK  BUTTCANE",
                    "gender":"man",
                    "gender_color":"blue",
                    "researcharea":"math",
                    "researcharea_color":"#8F3CCC"
                },
                {
                    "name":"MATTHEW E LANE",
                    "gender":"man",
                    "gender_color":"blue",
                    "researcharea":"math",
                    "researcharea_color":"#8F3CCC"
                }
            ]
        },
        {
            "name":"ALEXANDER  GAMBURD",
            "gender":"man",
            "gender_color":"blue",
            "researcharea":"math",
            "researcharea_color":"#8F3CCC",
            "children":[
                {
                    "name":"MICHAEL  MAGEE",
                    "gender":"man",
                    "gender_color":"blue",
                    "researcharea":"math",
                    "researcharea_color":"#8F3CCC"
                }
            ]
        },
        {
            "name":"YOUNGHAN  PARK",
            "gender":"man",
            "gender_color":"blue",
            "researcharea":"math",
            "researcharea_color":"#8F3CCC"
        },
        {
            "name":"SEAN T PAUL",
            "gender":"man",
            "gender_color":"blue",
            "researcharea":"math",
            "researcharea_color":"#8F3CCC"
        },
        {
            "name":"EDUARDO  DUENEZ",
            "gender":"man",
            "gender_color":"blue",
            "researcharea":"math",
            "researcharea_color":"#8F3CCC"
        },
        {
            "name":"MARK E MCKEE",
            "gender":"man",
            "gender_color":"blue",
            "researcharea":"math",
            "researcharea_color":"#8F3CCC"
        },
        {
            "name":"ANDREW R BOOKER",
            "gender":"man",
            "gender_color":"blue",
            "researcharea":"math",
            "researcharea_color":"#8F3CCC"
        },
        {
            "name":"GERGELY  HARCOS",
            "gender":"man",
            "gender_color":"blue",
            "researcharea":"math",
            "researcharea_color":"#8F3CCC"
        },
        {
            "name":"FLORIN  SPINU",
            "gender":"man",
            "gender_color":"blue",
            "researcharea":"math",
            "researcharea_color":"#8F3CCC"
        },
        {
            "name":"LIOR  SILBERMAN",
            "gender":"man",
            "gender_color":"blue",
            "researcharea":"math",
            "researcharea_color":"#8F3CCC"
        },
        {
            "name":"DJORDJE  MILICEVIC",
            "gender":"man",
            "gender_color":"blue",
            "researcharea":"math",
            "researcharea_color":"#8F3CCC"
        },
        {
            "name":"SIMON  MARSHALL",
            "gender":"man",
            "gender_color":"blue",
            "researcharea":"math",
            "researcharea_color":"#8F3CCC"
        },
        {
            "name":"JACOB  TSIMERMAN",
            "gender":"man",
            "gender_color":"blue",
            "researcharea":"math",
            "researcharea_color":"#8F3CCC"
        },
        {
            "name":"SALIM A ALTUG",
            "gender":"man",
            "gender_color":"blue",
            "researcharea":"math",
            "researcharea_color":"#8F3CCC"
        }
    ]
}