{
    "name":"DONNA  CELLANTE",
    "gender":"woman",
    "gender_color":"red",
    "researcharea":"computerscience",
    "researcharea_color":"#10887E",
    "children":[
        {
            "name":"MARCI  KLINGER",
            "gender":"woman",
            "gender_color":"red",
            "researcharea":"computerscience",
            "researcharea_color":"#10887E"
        },
        {
            "name":"APRIL  WIERZBOWSKI-KWIATKOWSKI",
            "gender":"woman",
            "gender_color":"red",
            "researcharea":"computerscience",
            "researcharea_color":"#10887E"
        },
        {
            "name":"TRACEY L CEKADA",
            "gender":"woman",
            "gender_color":"red",
            "researcharea":"computerscience",
            "researcharea_color":"#10887E"
        },
        {
            "name":"ROBERT  BADOWSKI",
            "gender":"man",
            "gender_color":"blue",
            "researcharea":"computerscience",
            "researcharea_color":"#10887E"
        },
        {
            "name":"DOMINIC  CINCOTTA",
            "gender":"man",
            "gender_color":"blue",
            "researcharea":"computerscience",
            "researcharea_color":"#10887E"
        }
    ]
}