{
    "name":"LOUIS LEON THURSTONE",
    "gender":"man",
    "gender_color":"blue",
    "researcharea":"neuro",
    "researcharea_color":"#F3E09A",
    "children":[
        {
            "name":"RALPH M REITAN",
            "gender":"man",
            "gender_color":"blue",
            "researcharea":"neuro",
            "researcharea_color":"#F3E09A",
            "children":[
                {
                    "name":"WILLIAM H GADDES",
                    "gender":"man",
                    "gender_color":"blue",
                    "researcharea":"neuro",
                    "researcharea_color":"#F3E09A"
                },
                {
                    "name":"GERALD  GOLDSTEIN",
                    "gender":"man",
                    "gender_color":"blue",
                    "researcharea":"neuro",
                    "researcharea_color":"#F3E09A"
                },
                {
                    "name":"IGOR  GRANT",
                    "gender":"man",
                    "gender_color":"blue",
                    "researcharea":"neuro",
                    "researcharea_color":"#F3E09A"
                },
                {
                    "name":"OSCAR ALBERT PARSONS",
                    "gender":"man",
                    "gender_color":"blue",
                    "researcharea":"neuro",
                    "researcharea_color":"#F3E09A"
                },
                {
                    "name":"BOB  GANT",
                    "gender":"man",
                    "gender_color":"blue",
                    "researcharea":"neuro",
                    "researcharea_color":"#F3E09A"
                },
                {
                    "name":"RAYMOND S DEAN",
                    "gender":"man",
                    "gender_color":"blue",
                    "researcharea":"neuro",
                    "researcharea_color":"#F3E09A",
                    "children":[
                        {
                            "name":"JEFFREY B TITUS",
                            "gender":"man",
                            "gender_color":"blue",
                            "researcharea":"neuro",
                            "researcharea_color":"#F3E09A"
                        }
                    ]
                }
            ]
        },
        {
            "name":"CALVIN W TAYLOR",
            "gender":"man",
            "gender_color":"blue",
            "researcharea":"psych",
            "researcharea_color":"#3CDE38",
            "children":[
                {
                    "name":"LAWRENCE R JAMES",
                    "gender":"man",
                    "gender_color":"blue",
                    "researcharea":"psych",
                    "researcharea_color":"#3CDE38",
                    "children":[
                        {
                            "name":"DEBRAH Z MIGETZ",
                            "gender":"woman",
                            "gender_color":"red",
                            "researcharea":"psych",
                            "researcharea_color":"#3CDE38"
                        },
                        {
                            "name":"SUSAN M BURROUGHS",
                            "gender":"woman",
                            "gender_color":"red",
                            "researcharea":"psych",
                            "researcharea_color":"#3CDE38"
                        },
                        {
                            "name":"JENNIFER L BOWLER",
                            "gender":"woman",
                            "gender_color":"red",
                            "researcharea":"psych",
                            "researcharea_color":"#3CDE38"
                        },
                        {
                            "name":"LOIS E TETRICK",
                            "gender":"woman",
                            "gender_color":"red",
                            "researcharea":"psych",
                            "researcharea_color":"#3CDE38",
                            "children":[
                                {
                                    "name":"LAURA  WHEELER POMS",
                                    "gender":"woman",
                                    "gender_color":"red",
                                    "researcharea":"psych",
                                    "researcharea_color":"#3CDE38"
                                },
                                {
                                    "name":"TIFFANY M BENNETT",
                                    "gender":"woman",
                                    "gender_color":"red",
                                    "researcharea":"psych",
                                    "researcharea_color":"#3CDE38"
                                },
                                {
                                    "name":"JORDAN M ROBBINS",
                                    "gender":"man",
                                    "gender_color":"blue",
                                    "researcharea":"psych",
                                    "researcharea_color":"#3CDE38"
                                },
                                {
                                    "name":"LUKE  BROOKS-SHESLER",
                                    "gender":"man",
                                    "gender_color":"blue",
                                    "researcharea":"psych",
                                    "researcharea_color":"#3CDE38"
                                },
                                {
                                    "name":"PHILLIP L GILMORE",
                                    "gender":"man",
                                    "gender_color":"blue",
                                    "researcharea":"psych",
                                    "researcharea_color":"#3CDE38"
                                },
                                {
                                    "name":"CLIFFORD R HAIMANN",
                                    "gender":"man",
                                    "gender_color":"blue",
                                    "researcharea":"psych",
                                    "researcharea_color":"#3CDE38"
                                },
                                {
                                    "name":"KENNETH S SHULTZ",
                                    "gender":"man",
                                    "gender_color":"blue",
                                    "researcharea":"psych",
                                    "researcharea_color":"#3CDE38"
                                },
                                {
                                    "name":"WALTER B PORR",
                                    "gender":"man",
                                    "gender_color":"blue",
                                    "researcharea":"psych",
                                    "researcharea_color":"#3CDE38"
                                }
                            ]
                        },
                        {
                            "name":"WILLIAM R WALTON",
                            "gender":"man",
                            "gender_color":"blue",
                            "researcharea":"psych",
                            "researcharea_color":"#3CDE38"
                        },
                        {
                            "name":"JEREMY L BOWERS SCHOEN",
                            "gender":"man",
                            "gender_color":"blue",
                            "researcharea":"psych",
                            "researcharea_color":"#3CDE38"
                        },
                        {
                            "name":"DANIEL R SMITH",
                            "gender":"man",
                            "gender_color":"blue",
                            "researcharea":"psych",
                            "researcharea_color":"#3CDE38"
                        },
                        {
                            "name":"MARK N BING",
                            "gender":"man",
                            "gender_color":"blue",
                            "researcharea":"psych",
                            "researcharea_color":"#3CDE38",
                            "children":[
                                {
                                    "name":"JOHN E SMOTHERS",
                                    "gender":"man",
                                    "gender_color":"blue",
                                    "researcharea":"psych",
                                    "researcharea_color":"#3CDE38"
                                },
                                {
                                    "name":"JAYSON B VANHOOK",
                                    "gender":"man",
                                    "gender_color":"blue",
                                    "researcharea":"psych",
                                    "researcharea_color":"#3CDE38"
                                }
                            ]
                        },
                        {
                            "name":"DAVID J WOEHR",
                            "gender":"man",
                            "gender_color":"blue",
                            "researcharea":"psych",
                            "researcharea_color":"#3CDE38",
                            "children":[
                                {
                                    "name":"JOANA  PIMENTEL",
                                    "gender":"woman",
                                    "gender_color":"red",
                                    "researcharea":"psych",
                                    "researcharea_color":"#3CDE38"
                                },
                                {
                                    "name":"MELINDA  FEHRMANN-BREMLEY",
                                    "gender":"woman",
                                    "gender_color":"red",
                                    "researcharea":"psych",
                                    "researcharea_color":"#3CDE38"
                                },
                                {
                                    "name":"ANGIE  ROSENBAUM",
                                    "gender":"woman",
                                    "gender_color":"red",
                                    "researcharea":"psych",
                                    "researcharea_color":"#3CDE38"
                                },
                                {
                                    "name":"ROBYN  MALDEGAN-YOUNGJOHN",
                                    "gender":"woman",
                                    "gender_color":"red",
                                    "researcharea":"psych",
                                    "researcharea_color":"#3CDE38"
                                },
                                {
                                    "name":"JOY  OLIVER",
                                    "gender":"woman",
                                    "gender_color":"red",
                                    "researcharea":"psych",
                                    "researcharea_color":"#3CDE38"
                                },
                                {
                                    "name":"JENNIFER  BURGESS",
                                    "gender":"woman",
                                    "gender_color":"red",
                                    "researcharea":"psych",
                                    "researcharea_color":"#3CDE38"
                                },
                                {
                                    "name":"AMANDA  BAUGUS",
                                    "gender":"woman",
                                    "gender_color":"red",
                                    "researcharea":"psych",
                                    "researcharea_color":"#3CDE38"
                                },
                                {
                                    "name":"ELIZABETH  MCGEE",
                                    "gender":"woman",
                                    "gender_color":"red",
                                    "researcharea":"psych",
                                    "researcharea_color":"#3CDE38"
                                },
                                {
                                    "name":"IRINA  COZMA",
                                    "gender":"woman",
                                    "gender_color":"red",
                                    "researcharea":"psych",
                                    "researcharea_color":"#3CDE38"
                                },
                                {
                                    "name":"JANE S THOMAS",
                                    "gender":"woman",
                                    "gender_color":"red",
                                    "researcharea":"psych",
                                    "researcharea_color":"#3CDE38"
                                },
                                {
                                    "name":"ALLEN  HUFFCUTT",
                                    "gender":"man",
                                    "gender_color":"blue",
                                    "researcharea":"psych",
                                    "researcharea_color":"#3CDE38"
                                },
                                {
                                    "name":"BRIAN J HOFFMANN",
                                    "gender":"man",
                                    "gender_color":"blue",
                                    "researcharea":"psych",
                                    "researcharea_color":"#3CDE38"
                                },
                                {
                                    "name":"ANDREW  LOIGNON",
                                    "gender":"man",
                                    "gender_color":"blue",
                                    "researcharea":"psych",
                                    "researcharea_color":"#3CDE38"
                                },
                                {
                                    "name":"MARK C BOWLER",
                                    "gender":"man",
                                    "gender_color":"blue",
                                    "researcharea":"psych",
                                    "researcharea_color":"#3CDE38"
                                },
                                {
                                    "name":"GREG  BERKA",
                                    "gender":"man",
                                    "gender_color":"blue",
                                    "researcharea":"psych",
                                    "researcharea_color":"#3CDE38"
                                },
                                {
                                    "name":"JOSH  BAZZY",
                                    "gender":"man",
                                    "gender_color":"blue",
                                    "researcharea":"psych",
                                    "researcharea_color":"#3CDE38"
                                },
                                {
                                    "name":"MATTHEW S FLEISHER",
                                    "gender":"man",
                                    "gender_color":"blue",
                                    "researcharea":"psych",
                                    "researcharea_color":"#3CDE38"
                                },
                                {
                                    "name":"MICHAEL J MILLER",
                                    "gender":"man",
                                    "gender_color":"blue",
                                    "researcharea":"psych",
                                    "researcharea_color":"#3CDE38"
                                },
                                {
                                    "name":"STEPHAN  GABY",
                                    "gender":"man",
                                    "gender_color":"blue",
                                    "researcharea":"psych",
                                    "researcharea_color":"#3CDE38"
                                },
                                {
                                    "name":"MICHAEL  MCCORMICK",
                                    "gender":"man",
                                    "gender_color":"blue",
                                    "researcharea":"psych",
                                    "researcharea_color":"#3CDE38"
                                },
                                {
                                    "name":"ANTHONY  MCBRIDE",
                                    "gender":"man",
                                    "gender_color":"blue",
                                    "researcharea":"psych",
                                    "researcharea_color":"#3CDE38"
                                },
                                {
                                    "name":"STEPHEN  JENNER",
                                    "gender":"man",
                                    "gender_color":"blue",
                                    "researcharea":"psych",
                                    "researcharea_color":"#3CDE38"
                                }
                            ]
                        },
                        {
                            "name":"MICHAEL  LIPPSTREU",
                            "gender":"man",
                            "gender_color":"blue",
                            "researcharea":"psych",
                            "researcharea_color":"#3CDE38"
                        },
                        {
                            "name":"JAMES M LEBRETON",
                            "gender":"man",
                            "gender_color":"blue",
                            "researcharea":"psych",
                            "researcharea_color":"#3CDE38",
                            "children":[
                                {
                                    "name":"STEFANIE A PLEMMONS",
                                    "gender":"woman",
                                    "gender_color":"red",
                                    "researcharea":"psych",
                                    "researcharea_color":"#3CDE38"
                                },
                                {
                                    "name":"LISA A SCHULTZ",
                                    "gender":"woman",
                                    "gender_color":"red",
                                    "researcharea":"psych",
                                    "researcharea_color":"#3CDE38"
                                },
                                {
                                    "name":"LAURELA B JOHNSON",
                                    "gender":"woman",
                                    "gender_color":"red",
                                    "researcharea":"psych",
                                    "researcharea_color":"#3CDE38"
                                },
                                {
                                    "name":"KELLY  SCHERER",
                                    "gender":"woman",
                                    "gender_color":"red",
                                    "researcharea":"psych",
                                    "researcharea_color":"#3CDE38"
                                },
                                {
                                    "name":"CRISTINA  THERIAULT",
                                    "gender":"woman",
                                    "gender_color":"red",
                                    "researcharea":"psych",
                                    "researcharea_color":"#3CDE38"
                                },
                                {
                                    "name":"AMANDA N MOELLER",
                                    "gender":"woman",
                                    "gender_color":"red",
                                    "researcharea":"psych",
                                    "researcharea_color":"#3CDE38"
                                },
                                {
                                    "name":"JANE  WU",
                                    "gender":"woman",
                                    "gender_color":"red",
                                    "researcharea":"psych",
                                    "researcharea_color":"#3CDE38"
                                },
                                {
                                    "name":"DINA  KRASIKOVA",
                                    "gender":"woman",
                                    "gender_color":"red",
                                    "researcharea":"psych",
                                    "researcharea_color":"#3CDE38"
                                },
                                {
                                    "name":"JESSE S MICHEL",
                                    "gender":"man",
                                    "gender_color":"blue",
                                    "researcharea":"psych",
                                    "researcharea_color":"#3CDE38",
                                    "children":[
                                        {
                                            "name":"ERICA  BRITTON",
                                            "gender":"woman",
                                            "gender_color":"red",
                                            "researcharea":"psych",
                                            "researcharea_color":"#3CDE38"
                                        }
                                    ]
                                },
                                {
                                    "name":"MICHAEL B HARGIS",
                                    "gender":"man",
                                    "gender_color":"blue",
                                    "researcharea":"psych",
                                    "researcharea_color":"#3CDE38"
                                },
                                {
                                    "name":"RUSTIN D MEYER",
                                    "gender":"man",
                                    "gender_color":"blue",
                                    "researcharea":"psych",
                                    "researcharea_color":"#3CDE38"
                                },
                                {
                                    "name":"MICHAEL A BAYSINGER",
                                    "gender":"man",
                                    "gender_color":"blue",
                                    "researcharea":"psych",
                                    "researcharea_color":"#3CDE38"
                                },
                                {
                                    "name":"LEVI  SHIVERDECKER",
                                    "gender":"man",
                                    "gender_color":"blue",
                                    "researcharea":"psych",
                                    "researcharea_color":"#3CDE38"
                                }
                            ]
                        }
                    ]
                }
            ]
        },
        {
            "name":"CLYDE H COOMBS",
            "gender":"man",
            "gender_color":"blue",
            "researcharea":"neuro",
            "researcharea_color":"#F3E09A",
            "children":[
                {
                    "name":"AMOS  TVERSKY",
                    "gender":"man",
                    "gender_color":"blue",
                    "researcharea":"neuro",
                    "researcharea_color":"#F3E09A",
                    "children":[
                        {
                            "name":"VALERIE  REYNA",
                            "gender":"woman",
                            "gender_color":"red",
                            "researcharea":"neuro",
                            "researcharea_color":"#F3E09A"
                        },
                        {
                            "name":"DANIEL  KAHNEMAN",
                            "gender":"man",
                            "gender_color":"blue",
                            "researcharea":"neuro",
                            "researcharea_color":"#F3E09A",
                            "children":[
                                {
                                    "name":"DALE W GRIFFIN",
                                    "gender":"man",
                                    "gender_color":"blue",
                                    "researcharea":"neuro",
                                    "researcharea_color":"#F3E09A",
                                    "children":[
                                        {
                                            "name":"SANDRA L MURRAY",
                                            "gender":"woman",
                                            "gender_color":"red",
                                            "researcharea":"psych",
                                            "researcharea_color":"#3CDE38",
                                            "children":[
                                                {
                                                    "name":"SARAH  GOMILLION",
                                                    "gender":"woman",
                                                    "gender_color":"red",
                                                    "researcharea":"psych",
                                                    "researcharea_color":"#3CDE38"
                                                },
                                                {
                                                    "name":"MAYA  ALONI",
                                                    "gender":"woman",
                                                    "gender_color":"red",
                                                    "researcharea":"psych",
                                                    "researcharea_color":"#3CDE38"
                                                },
                                                {
                                                    "name":"SADIE  LEDER",
                                                    "gender":"woman",
                                                    "gender_color":"red",
                                                    "researcharea":"psych",
                                                    "researcharea_color":"#3CDE38"
                                                },
                                                {
                                                    "name":"JAYE L DERRICK",
                                                    "gender":"woman",
                                                    "gender_color":"red",
                                                    "researcharea":"psych",
                                                    "researcharea_color":"#3CDE38",
                                                    "children":[
                                                        {
                                                            "name":"SANA  HADDAD",
                                                            "gender":"woman",
                                                            "gender_color":"red",
                                                            "researcharea":"psych",
                                                            "researcharea_color":"#3CDE38"
                                                        },
                                                        {
                                                            "name":"MAGGIE  BRITTON",
                                                            "gender":"woman",
                                                            "gender_color":"red",
                                                            "researcharea":"psych",
                                                            "researcharea_color":"#3CDE38"
                                                        },
                                                        {
                                                            "name":"MEISAM  VAHEDI",
                                                            "gender":"woman",
                                                            "gender_color":"red",
                                                            "researcharea":"psych",
                                                            "researcharea_color":"#3CDE38"
                                                        },
                                                        {
                                                            "name":"ZACHARY  BAKER",
                                                            "gender":"man",
                                                            "gender_color":"blue",
                                                            "researcharea":"psych",
                                                            "researcharea_color":"#3CDE38"
                                                        },
                                                        {
                                                            "name":"DAVID  WITTKOWER",
                                                            "gender":"man",
                                                            "gender_color":"blue",
                                                            "researcharea":"psych",
                                                            "researcharea_color":"#3CDE38"
                                                        },
                                                        {
                                                            "name":"JACE  PIERCE",
                                                            "gender":"man",
                                                            "gender_color":"blue",
                                                            "researcharea":"psych",
                                                            "researcharea_color":"#3CDE38"
                                                        }
                                                    ]
                                                },
                                                {
                                                    "name":"BRIANNA  HARRIS",
                                                    "gender":"woman",
                                                    "gender_color":"red",
                                                    "researcharea":"psych",
                                                    "researcharea_color":"#3CDE38"
                                                },
                                                {
                                                    "name":"GINA  BELLAVIA",
                                                    "gender":"woman",
                                                    "gender_color":"red",
                                                    "researcharea":"psych",
                                                    "researcharea_color":"#3CDE38"
                                                },
                                                {
                                                    "name":"PAUL  ROSE",
                                                    "gender":"man",
                                                    "gender_color":"blue",
                                                    "researcharea":"psych",
                                                    "researcharea_color":"#3CDE38"
                                                }
                                            ]
                                        }
                                    ]
                                },
                                {
                                    "name":"ZIV  CARMON",
                                    "gender":"man",
                                    "gender_color":"blue",
                                    "researcharea":"psych",
                                    "researcharea_color":"#3CDE38"
                                },
                                {
                                    "name":"MICHAEL  KUBOVY",
                                    "gender":"man",
                                    "gender_color":"blue",
                                    "researcharea":"neuro",
                                    "researcharea_color":"#F3E09A"
                                }
                            ]
                        },
                        {
                            "name":"STEVEN  SLOMAN",
                            "gender":"man",
                            "gender_color":"blue",
                            "researcharea":"psych",
                            "researcharea_color":"#3CDE38",
                            "children":[
                                {
                                    "name":"JEFFREY C ZEMLA",
                                    "gender":"man",
                                    "gender_color":"blue",
                                    "researcharea":"psych",
                                    "researcharea_color":"#3CDE38"
                                },
                                {
                                    "name":"PHILIP M FERNBACH",
                                    "gender":"man",
                                    "gender_color":"blue",
                                    "researcharea":"psych",
                                    "researcharea_color":"#3CDE38"
                                }
                            ]
                        },
                        {
                            "name":"RAN  HASSIN",
                            "gender":"man",
                            "gender_color":"blue",
                            "researcharea":"psych",
                            "researcharea_color":"#3CDE38",
                            "children":[
                                {
                                    "name":"TALI  KLEIMAN",
                                    "gender":"woman",
                                    "gender_color":"red",
                                    "researcharea":"psych",
                                    "researcharea_color":"#3CDE38"
                                },
                                {
                                    "name":"RASHA  KARDOSH",
                                    "gender":"woman",
                                    "gender_color":"red",
                                    "researcharea":"psych",
                                    "researcharea_color":"#3CDE38"
                                },
                                {
                                    "name":"VERONICA  DUDAREV",
                                    "gender":"woman",
                                    "gender_color":"red",
                                    "researcharea":"psych",
                                    "researcharea_color":"#3CDE38"
                                },
                                {
                                    "name":"MAXIM  MILYAVSKY",
                                    "gender":"man",
                                    "gender_color":"blue",
                                    "researcharea":"psych",
                                    "researcharea_color":"#3CDE38"
                                },
                                {
                                    "name":"HILLEL  AVIEZER",
                                    "gender":"man",
                                    "gender_color":"blue",
                                    "researcharea":"psych",
                                    "researcharea_color":"#3CDE38"
                                },
                                {
                                    "name":"ASAEL  SKLAR",
                                    "gender":"man",
                                    "gender_color":"blue",
                                    "researcharea":"psych",
                                    "researcharea_color":"#3CDE38"
                                },
                                {
                                    "name":"ALON  GOLDSTEIN",
                                    "gender":"man",
                                    "gender_color":"blue",
                                    "researcharea":"psych",
                                    "researcharea_color":"#3CDE38"
                                }
                            ]
                        }
                    ]
                },
                {
                    "name":"WILLIAM  HAYS",
                    "gender":"man",
                    "gender_color":"blue",
                    "researcharea":"neuro",
                    "researcharea_color":"#F3E09A",
                    "children":[
                        {
                            "name":"MYRON LEE BRAUNSTEIN",
                            "gender":"man",
                            "gender_color":"blue",
                            "researcharea":"psych",
                            "researcharea_color":"#3CDE38",
                            "children":[
                                {
                                    "name":"JESSICA A TURNER",
                                    "gender":"woman",
                                    "gender_color":"red",
                                    "researcharea":"psych",
                                    "researcharea_color":"#3CDE38"
                                },
                                {
                                    "name":"JOHN WILLIAM PAYNE",
                                    "gender":"man",
                                    "gender_color":"blue",
                                    "researcharea":"psych",
                                    "researcharea_color":"#3CDE38"
                                },
                                {
                                    "name":"GEORGE JOHN ANDERSEN",
                                    "gender":"man",
                                    "gender_color":"blue",
                                    "researcharea":"psych",
                                    "researcharea_color":"#3CDE38",
                                    "children":[
                                        {
                                            "name":"JULIE J KANG",
                                            "gender":"woman",
                                            "gender_color":"red",
                                            "researcharea":"psych",
                                            "researcharea_color":"#3CDE38"
                                        },
                                        {
                                            "name":"AMY HELEN GUINDON",
                                            "gender":"woman",
                                            "gender_color":"red",
                                            "researcharea":"psych",
                                            "researcharea_color":"#3CDE38"
                                        },
                                        {
                                            "name":"RUI  NI",
                                            "gender":"man",
                                            "gender_color":"blue",
                                            "researcharea":"neuro",
                                            "researcharea_color":"#F3E09A"
                                        },
                                        {
                                            "name":"JEFFREY DENNIS BOWER",
                                            "gender":"man",
                                            "gender_color":"blue",
                                            "researcharea":"psych",
                                            "researcharea_color":"#3CDE38"
                                        },
                                        {
                                            "name":"PAUL  ATCHLEY",
                                            "gender":"man",
                                            "gender_color":"blue",
                                            "researcharea":"psych",
                                            "researcharea_color":"#3CDE38",
                                            "children":[
                                                {
                                                    "name":"LESA  HOFFMAN",
                                                    "gender":"woman",
                                                    "gender_color":"red",
                                                    "researcharea":"psych",
                                                    "researcharea_color":"#3CDE38"
                                                },
                                                {
                                                    "name":"JEFFREY  DRESSEL",
                                                    "gender":"man",
                                                    "gender_color":"blue",
                                                    "researcharea":"psych",
                                                    "researcharea_color":"#3CDE38"
                                                },
                                                {
                                                    "name":"MARK S CHAN",
                                                    "gender":"man",
                                                    "gender_color":"blue",
                                                    "researcharea":"psych",
                                                    "researcharea_color":"#3CDE38"
                                                }
                                            ]
                                        }
                                    ]
                                },
                                {
                                    "name":"CRAIG W SAUER",
                                    "gender":"man",
                                    "gender_color":"blue",
                                    "researcharea":"psych",
                                    "researcharea_color":"#3CDE38"
                                },
                                {
                                    "name":"KEREM  OZKAN",
                                    "gender":"man",
                                    "gender_color":"blue",
                                    "researcharea":"psych",
                                    "researcharea_color":"#3CDE38"
                                }
                            ]
                        }
                    ]
                }
            ]
        },
        {
            "name":"HARRY  UPSHAW",
            "gender":"man",
            "gender_color":"blue",
            "researcharea":"psych",
            "researcharea_color":"#3CDE38",
            "children":[
                {
                    "name":"THOMAS  OSTROM",
                    "gender":"man",
                    "gender_color":"blue",
                    "researcharea":"psych",
                    "researcharea_color":"#3CDE38",
                    "children":[
                        {
                            "name":"PATRICIA  DEVINE",
                            "gender":"woman",
                            "gender_color":"red",
                            "researcharea":"neuro",
                            "researcharea_color":"#F3E09A",
                            "children":[
                                {
                                    "name":"JENNIFER T KUBOTA",
                                    "gender":"woman",
                                    "gender_color":"red",
                                    "researcharea":"neuro",
                                    "researcharea_color":"#F3E09A"
                                },
                                {
                                    "name":"WILLIAM T L COX",
                                    "gender":"man",
                                    "gender_color":"blue",
                                    "researcharea":"psych",
                                    "researcharea_color":"#3CDE38",
                                    "children":[
                                        {
                                            "name":"JANET S HYDE",
                                            "gender":"woman",
                                            "gender_color":"red",
                                            "researcharea":"psych",
                                            "researcharea_color":"#3CDE38",
                                            "children":[
                                                {
                                                    "name":"MYESHIA N PRICE",
                                                    "gender":"woman",
                                                    "gender_color":"red",
                                                    "researcharea":"psych",
                                                    "researcharea_color":"#3CDE38"
                                                },
                                                {
                                                    "name":"SABRA L KATZ-WISE",
                                                    "gender":"woman",
                                                    "gender_color":"red",
                                                    "researcharea":"psych",
                                                    "researcharea_color":"#3CDE38"
                                                },
                                                {
                                                    "name":"HEATHER A PRIESS",
                                                    "gender":"woman",
                                                    "gender_color":"red",
                                                    "researcharea":"psych",
                                                    "researcharea_color":"#3CDE38"
                                                },
                                                {
                                                    "name":"SARA M LINDBERG",
                                                    "gender":"woman",
                                                    "gender_color":"red",
                                                    "researcharea":"psych",
                                                    "researcharea_color":"#3CDE38"
                                                },
                                                {
                                                    "name":"NICOLE M ELSE-QUEST",
                                                    "gender":"woman",
                                                    "gender_color":"red",
                                                    "researcharea":"psych",
                                                    "researcharea_color":"#3CDE38",
                                                    "children":[
                                                        {
                                                            "name":"EMILY  MORSE",
                                                            "gender":"woman",
                                                            "gender_color":"red",
                                                            "researcharea":"psych",
                                                            "researcharea_color":"#3CDE38"
                                                        }
                                                    ]
                                                }
                                            ]
                                        },
                                        {
                                            "name":"ALYSSA  BISCHMANN",
                                            "gender":"woman",
                                            "gender_color":"red",
                                            "researcharea":"psych",
                                            "researcharea_color":"#3CDE38"
                                        }
                                    ]
                                },
                                {
                                    "name":"PATRICK S FORSCHER",
                                    "gender":"man",
                                    "gender_color":"blue",
                                    "researcharea":"psych",
                                    "researcharea_color":"#3CDE38"
                                }
                            ]
                        },
                        {
                            "name":"CAROL MIEHE WERNER",
                            "gender":"woman",
                            "gender_color":"red",
                            "researcharea":"psych",
                            "researcharea_color":"#3CDE38",
                            "children":[
                                {
                                    "name":"MICHAEL  STRUBE",
                                    "gender":"man",
                                    "gender_color":"blue",
                                    "researcharea":"psych",
                                    "researcharea_color":"#3CDE38",
                                    "children":[
                                        {
                                            "name":"ELENA V STEPANOVA",
                                            "gender":"woman",
                                            "gender_color":"red",
                                            "researcharea":"psych",
                                            "researcharea_color":"#3CDE38"
                                        },
                                        {
                                            "name":"INBAL  GURARI",
                                            "gender":"woman",
                                            "gender_color":"red",
                                            "researcharea":"psych",
                                            "researcharea_color":"#3CDE38"
                                        },
                                        {
                                            "name":"AMY D WATERMAN",
                                            "gender":"woman",
                                            "gender_color":"red",
                                            "researcharea":"psych",
                                            "researcharea_color":"#3CDE38"
                                        },
                                        {
                                            "name":"NICHOLAS S HOLTZMAN",
                                            "gender":"man",
                                            "gender_color":"blue",
                                            "researcharea":"psych",
                                            "researcharea_color":"#3CDE38",
                                            "children":[
                                                {
                                                    "name":"CLINT E JOHNSON",
                                                    "gender":"man",
                                                    "gender_color":"blue",
                                                    "researcharea":"psych",
                                                    "researcharea_color":"#3CDE38"
                                                }
                                            ]
                                        },
                                        {
                                            "name":"WAYNE K RHEE",
                                            "gender":"man",
                                            "gender_color":"blue",
                                            "researcharea":"psych",
                                            "researcharea_color":"#3CDE38"
                                        }
                                    ]
                                }
                            ]
                        },
                        {
                            "name":"CLAUDE  STEELE",
                            "gender":"man",
                            "gender_color":"blue",
                            "researcharea":"psych",
                            "researcharea_color":"#3CDE38",
                            "children":[
                                {
                                    "name":"TECETA E THOMAS",
                                    "gender":"woman",
                                    "gender_color":"red",
                                    "researcharea":"psych",
                                    "researcharea_color":"#3CDE38"
                                },
                                {
                                    "name":"MARY C MURPHY",
                                    "gender":"woman",
                                    "gender_color":"red",
                                    "researcharea":"psych",
                                    "researcharea_color":"#3CDE38",
                                    "children":[
                                        {
                                            "name":"HEIDI E WILLIAMS",
                                            "gender":"woman",
                                            "gender_color":"red",
                                            "researcharea":"psych",
                                            "researcharea_color":"#3CDE38"
                                        },
                                        {
                                            "name":"ELIZABETH A CANNING",
                                            "gender":"woman",
                                            "gender_color":"red",
                                            "researcharea":"psych",
                                            "researcharea_color":"#3CDE38"
                                        },
                                        {
                                            "name":"KATHERINE  MUENKS",
                                            "gender":"woman",
                                            "gender_color":"red",
                                            "researcharea":"psych",
                                            "researcharea_color":"#3CDE38"
                                        },
                                        {
                                            "name":"DORAINNE  LEVY",
                                            "gender":"woman",
                                            "gender_color":"red",
                                            "researcharea":"psych",
                                            "researcharea_color":"#3CDE38"
                                        },
                                        {
                                            "name":"SHAHANA  ANSARI",
                                            "gender":"woman",
                                            "gender_color":"red",
                                            "researcharea":"psych",
                                            "researcharea_color":"#3CDE38"
                                        },
                                        {
                                            "name":"ELISE  OZIER",
                                            "gender":"woman",
                                            "gender_color":"red",
                                            "researcharea":"psych",
                                            "researcharea_color":"#3CDE38"
                                        },
                                        {
                                            "name":"KATHRYN M KROEPER",
                                            "gender":"woman",
                                            "gender_color":"red",
                                            "researcharea":"psych",
                                            "researcharea_color":"#3CDE38"
                                        },
                                        {
                                            "name":"EVELYN  CARTER",
                                            "gender":"woman",
                                            "gender_color":"red",
                                            "researcharea":"psych",
                                            "researcharea_color":"#3CDE38"
                                        },
                                        {
                                            "name":"KATHERINE T U EMERSON",
                                            "gender":"woman",
                                            "gender_color":"red",
                                            "researcharea":"psych",
                                            "researcharea_color":"#3CDE38"
                                        },
                                        {
                                            "name":"JULIAN  RUCKER",
                                            "gender":"man",
                                            "gender_color":"blue",
                                            "researcharea":"psych",
                                            "researcharea_color":"#3CDE38"
                                        }
                                    ]
                                },
                                {
                                    "name":"GREG  WALTON",
                                    "gender":"man",
                                    "gender_color":"blue",
                                    "researcharea":"psych",
                                    "researcharea_color":"#3CDE38",
                                    "children":[
                                        {
                                            "name":"LAUREN J AGUILAR",
                                            "gender":"woman",
                                            "gender_color":"red",
                                            "researcharea":"psych",
                                            "researcharea_color":"#3CDE38"
                                        },
                                        {
                                            "name":"TONI  KENTHIRARAJAH",
                                            "gender":"woman",
                                            "gender_color":"red",
                                            "researcharea":"psych",
                                            "researcharea_color":"#3CDE38"
                                        },
                                        {
                                            "name":"VALERIE JONES TAYLOR",
                                            "gender":"woman",
                                            "gender_color":"red",
                                            "researcharea":"psych",
                                            "researcharea_color":"#3CDE38"
                                        },
                                        {
                                            "name":"VERONIKA  JOB",
                                            "gender":"woman",
                                            "gender_color":"red",
                                            "researcharea":"psych",
                                            "researcharea_color":"#3CDE38"
                                        },
                                        {
                                            "name":"TIFFANY  BRANNON",
                                            "gender":"woman",
                                            "gender_color":"red",
                                            "researcharea":"psych",
                                            "researcharea_color":"#3CDE38"
                                        },
                                        {
                                            "name":" JASON  OKONOFUA",
                                            "gender":"man",
                                            "gender_color":"blue",
                                            "researcharea":"psych",
                                            "researcharea_color":"#3CDE38"
                                        },
                                        {
                                            "name":"DAVID  PAUNESKU",
                                            "gender":"man",
                                            "gender_color":"blue",
                                            "researcharea":"psych",
                                            "researcharea_color":"#3CDE38"
                                        },
                                        {
                                            "name":"CHRISTOPHER  BRYAN",
                                            "gender":"man",
                                            "gender_color":"blue",
                                            "researcharea":"psych",
                                            "researcharea_color":"#3CDE38"
                                        }
                                    ]
                                },
                                {
                                    "name":"GEOFFREY  COHEN",
                                    "gender":"man",
                                    "gender_color":"blue",
                                    "researcharea":"psych",
                                    "researcharea_color":"#3CDE38",
                                    "children":[
                                        {
                                            "name":"STACY M FAMBRO",
                                            "gender":"woman",
                                            "gender_color":"red",
                                            "researcharea":"psych",
                                            "researcharea_color":"#3CDE38"
                                        },
                                        {
                                            "name":"GREGORY M WALTON",
                                            "gender":"man",
                                            "gender_color":"blue",
                                            "researcharea":"psych",
                                            "researcharea_color":"#3CDE38"
                                        },
                                        {
                                            "name":"ERIC L UHLMANN",
                                            "gender":"man",
                                            "gender_color":"blue",
                                            "researcharea":"psych",
                                            "researcharea_color":"#3CDE38"
                                        },
                                        {
                                            "name":"KODY  MANKE",
                                            "gender":"man",
                                            "gender_color":"blue",
                                            "researcharea":"psych",
                                            "researcharea_color":"#3CDE38"
                                        },
                                        {
                                            "name":"JOSEPH T POWERS",
                                            "gender":"man",
                                            "gender_color":"blue",
                                            "researcharea":"psych",
                                            "researcharea_color":"#3CDE38"
                                        }
                                    ]
                                },
                                {
                                    "name":"STEVE J SPENCER",
                                    "gender":"man",
                                    "gender_color":"blue",
                                    "researcharea":"psych",
                                    "researcharea_color":"#3CDE38",
                                    "children":[
                                        {
                                            "name":"MANDY  FORREST",
                                            "gender":"woman",
                                            "gender_color":"red",
                                            "researcharea":"psych",
                                            "researcharea_color":"#3CDE38"
                                        },
                                        {
                                            "name":"CRYSTAL  TSE",
                                            "gender":"woman",
                                            "gender_color":"red",
                                            "researcharea":"psych",
                                            "researcharea_color":"#3CDE38"
                                        },
                                        {
                                            "name":"CHRISTINE  LOGEL",
                                            "gender":"woman",
                                            "gender_color":"red",
                                            "researcharea":"psych",
                                            "researcharea_color":"#3CDE38"
                                        },
                                        {
                                            "name":"ETSUKO HOSHINO BROWNE",
                                            "gender":"woman",
                                            "gender_color":"red",
                                            "researcharea":"psych",
                                            "researcharea_color":"#3CDE38"
                                        },
                                        {
                                            "name":"ERIN  STRAHAN",
                                            "gender":"woman",
                                            "gender_color":"red",
                                            "researcharea":"psych",
                                            "researcharea_color":"#3CDE38"
                                        },
                                        {
                                            "name":"CHRISTIE  LOMORE",
                                            "gender":"woman",
                                            "gender_color":"red",
                                            "researcharea":"psych",
                                            "researcharea_color":"#3CDE38"
                                        },
                                        {
                                            "name":"DIANE M QUINN",
                                            "gender":"woman",
                                            "gender_color":"red",
                                            "researcharea":"psych",
                                            "researcharea_color":"#3CDE38",
                                            "children":[
                                                {
                                                    "name":"VALERIE A EARNSHAW",
                                                    "gender":"woman",
                                                    "gender_color":"red",
                                                    "researcharea":"psych",
                                                    "researcharea_color":"#3CDE38"
                                                },
                                                {
                                                    "name":"ELIZABETH K LAWNER",
                                                    "gender":"woman",
                                                    "gender_color":"red",
                                                    "researcharea":"psych",
                                                    "researcharea_color":"#3CDE38"
                                                },
                                                {
                                                    "name":"NICOLE M OVERSTREET",
                                                    "gender":"woman",
                                                    "gender_color":"red",
                                                    "researcharea":"psych",
                                                    "researcharea_color":"#3CDE38"
                                                },
                                                {
                                                    "name":"KIMBERLY J BRENCHLEY",
                                                    "gender":"woman",
                                                    "gender_color":"red",
                                                    "researcharea":"psych",
                                                    "researcharea_color":"#3CDE38"
                                                },
                                                {
                                                    "name":"STEPHENIE R CHAUDOIR",
                                                    "gender":"woman",
                                                    "gender_color":"red",
                                                    "researcharea":"psych",
                                                    "researcharea_color":"#3CDE38"
                                                },
                                                {
                                                    "name":"DIANA M MILILLO",
                                                    "gender":"woman",
                                                    "gender_color":"red",
                                                    "researcharea":"psych",
                                                    "researcharea_color":"#3CDE38"
                                                },
                                                {
                                                    "name":"RACHEL W KALLEN",
                                                    "gender":"woman",
                                                    "gender_color":"red",
                                                    "researcharea":"psych",
                                                    "researcharea_color":"#3CDE38"
                                                },
                                                {
                                                    "name":"EILEEN V PITPITAN",
                                                    "gender":"woman",
                                                    "gender_color":"red",
                                                    "researcharea":"psych",
                                                    "researcharea_color":"#3CDE38"
                                                },
                                                {
                                                    "name":"BRADLEY  PAN-WEISZ",
                                                    "gender":"man",
                                                    "gender_color":"blue",
                                                    "researcharea":"psych",
                                                    "researcharea_color":"#3CDE38"
                                                }
                                            ]
                                        },
                                        {
                                            "name":"CONNIE T WOLFE",
                                            "gender":"woman",
                                            "gender_color":"red",
                                            "researcharea":"psych",
                                            "researcharea_color":"#3CDE38"
                                        },
                                        {
                                            "name":"PAUL G DAVIES",
                                            "gender":"man",
                                            "gender_color":"blue",
                                            "researcharea":"psych",
                                            "researcharea_color":"#3CDE38"
                                        },
                                        {
                                            "name":"CHRISTIAN  JORDAN",
                                            "gender":"man",
                                            "gender_color":"blue",
                                            "researcharea":"psych",
                                            "researcharea_color":"#3CDE38"
                                        },
                                        {
                                            "name":"ALEX  GUNZ",
                                            "gender":"man",
                                            "gender_color":"blue",
                                            "researcharea":"psych",
                                            "researcharea_color":"#3CDE38"
                                        },
                                        {
                                            "name":"DAVID  CWIR",
                                            "gender":"man",
                                            "gender_color":"blue",
                                            "researcharea":"psych",
                                            "researcharea_color":"#3CDE38"
                                        },
                                        {
                                            "name":"DANIEL  NALDONY",
                                            "gender":"man",
                                            "gender_color":"blue",
                                            "researcharea":"psych",
                                            "researcharea_color":"#3CDE38"
                                        },
                                        {
                                            "name":"JUSTIN  FRIESEN",
                                            "gender":"man",
                                            "gender_color":"blue",
                                            "researcharea":"psych",
                                            "researcharea_color":"#3CDE38"
                                        },
                                        {
                                            "name":"JOSHUA  CORRELL",
                                            "gender":"man",
                                            "gender_color":"blue",
                                            "researcharea":"psych",
                                            "researcharea_color":"#3CDE38"
                                        },
                                        {
                                            "name":"HENRY  DANSO",
                                            "gender":"man",
                                            "gender_color":"blue",
                                            "researcharea":"psych",
                                            "researcharea_color":"#3CDE38"
                                        },
                                        {
                                            "name":"DAVID  NUSSBAUM",
                                            "gender":"man",
                                            "gender_color":"blue",
                                            "researcharea":"psych",
                                            "researcharea_color":"#3CDE38"
                                        }
                                    ]
                                }
                            ]
                        },
                        {
                            "name":"CONSTANTINE  SEDIKIDES",
                            "gender":"man",
                            "gender_color":"blue",
                            "researcharea":"psych",
                            "researcharea_color":"#3CDE38"
                        },
                        {
                            "name":"JOHN  EDWARDS",
                            "gender":"man",
                            "gender_color":"blue",
                            "researcharea":"neuro",
                            "researcharea_color":"#F3E09A",
                            "children":[
                                {
                                    "name":"DANIEL J KRUGER",
                                    "gender":"man",
                                    "gender_color":"blue",
                                    "researcharea":"neuro",
                                    "researcharea_color":"#F3E09A"
                                }
                            ]
                        },
                        {
                            "name":"JOHN  PRYOR",
                            "gender":"man",
                            "gender_color":"blue",
                            "researcharea":"psych",
                            "researcharea_color":"#3CDE38",
                            "children":[
                                {
                                    "name":"SHAERICA R JACKSON",
                                    "gender":"woman",
                                    "gender_color":"red",
                                    "researcharea":"psych",
                                    "researcharea_color":"#3CDE38"
                                },
                                {
                                    "name":"SHERLYN D ROBINSON",
                                    "gender":"woman",
                                    "gender_color":"red",
                                    "researcharea":"psych",
                                    "researcharea_color":"#3CDE38"
                                }
                            ]
                        },
                        {
                            "name":"JOHN H LINGLE",
                            "gender":"man",
                            "gender_color":"blue",
                            "researcharea":"psych",
                            "researcharea_color":"#3CDE38"
                        },
                        {
                            "name":"RICHARD  PETTY",
                            "gender":"man",
                            "gender_color":"blue",
                            "researcharea":"psych",
                            "researcharea_color":"#3CDE38",
                            "children":[
                                {
                                    "name":"BRITTANY L SHOOTS-REINHARD",
                                    "gender":"woman",
                                    "gender_color":"red",
                                    "researcharea":"psych",
                                    "researcharea_color":"#3CDE38"
                                },
                                {
                                    "name":"INDIA R JOHNSON",
                                    "gender":"woman",
                                    "gender_color":"red",
                                    "researcharea":"psych",
                                    "researcharea_color":"#3CDE38"
                                },
                                {
                                    "name":"LISA  EVANS",
                                    "gender":"woman",
                                    "gender_color":"red",
                                    "researcharea":"psych",
                                    "researcharea_color":"#3CDE38"
                                },
                                {
                                    "name":"MELISSA J BEERS",
                                    "gender":"woman",
                                    "gender_color":"red",
                                    "researcharea":"psych",
                                    "researcharea_color":"#3CDE38"
                                },
                                {
                                    "name":"KENNETH G DEMARREE",
                                    "gender":"man",
                                    "gender_color":"blue",
                                    "researcharea":"psych",
                                    "researcharea_color":"#3CDE38",
                                    "children":[
                                        {
                                            "name":"CORY J CLARK",
                                            "gender":"man",
                                            "gender_color":"blue",
                                            "researcharea":"psych",
                                            "researcharea_color":"#3CDE38"
                                        }
                                    ]
                                },
                                {
                                    "name":"LUCAS  HINSENKAMP",
                                    "gender":"man",
                                    "gender_color":"blue",
                                    "researcharea":"psych",
                                    "researcharea_color":"#3CDE38"
                                },
                                {
                                    "name":"GEOFFREY R DURSO",
                                    "gender":"man",
                                    "gender_color":"blue",
                                    "researcharea":"psych",
                                    "researcharea_color":"#3CDE38"
                                },
                                {
                                    "name":"DUANE T WEGENER",
                                    "gender":"man",
                                    "gender_color":"blue",
                                    "researcharea":"psych",
                                    "researcharea_color":"#3CDE38",
                                    "children":[
                                        {
                                            "name":"VANESSA  SAWICKI",
                                            "gender":"woman",
                                            "gender_color":"red",
                                            "researcharea":"psych",
                                            "researcharea_color":"#3CDE38"
                                        },
                                        {
                                            "name":"ANN E HOOVER",
                                            "gender":"woman",
                                            "gender_color":"red",
                                            "researcharea":"psych",
                                            "researcharea_color":"#3CDE38"
                                        },
                                        {
                                            "name":"KEVIN L BLANKENSHIP",
                                            "gender":"man",
                                            "gender_color":"blue",
                                            "researcharea":"psych",
                                            "researcharea_color":"#3CDE38"
                                        },
                                        {
                                            "name":"JASON K CLARK",
                                            "gender":"man",
                                            "gender_color":"blue",
                                            "researcharea":"psych",
                                            "researcharea_color":"#3CDE38",
                                            "children":[
                                                {
                                                    "name":"NOEL  TITUS",
                                                    "gender":"man",
                                                    "gender_color":"blue",
                                                    "researcharea":"psych",
                                                    "researcharea_color":"#3CDE38"
                                                }
                                            ]
                                        },
                                        {
                                            "name":"PHILIP J COLLINS",
                                            "gender":"man",
                                            "gender_color":"blue",
                                            "researcharea":"psych",
                                            "researcharea_color":"#3CDE38"
                                        },
                                        {
                                            "name":"JASON T REED",
                                            "gender":"man",
                                            "gender_color":"blue",
                                            "researcharea":"psych",
                                            "researcharea_color":"#3CDE38"
                                        }
                                    ]
                                },
                                {
                                    "name":"PABLO  BRINOL",
                                    "gender":"man",
                                    "gender_color":"blue",
                                    "researcharea":"psych",
                                    "researcharea_color":"#3CDE38",
                                    "children":[
                                        {
                                            "name":"DAVID  SANTOS",
                                            "gender":"man",
                                            "gender_color":"blue",
                                            "researcharea":"psych",
                                            "researcharea_color":"#3CDE38"
                                        }
                                    ]
                                },
                                {
                                    "name":"GEORGE Y BIZER",
                                    "gender":"man",
                                    "gender_color":"blue",
                                    "researcharea":"psych",
                                    "researcharea_color":"#3CDE38"
                                },
                                {
                                    "name":"JEFF T LARSEN",
                                    "gender":"man",
                                    "gender_color":"blue",
                                    "researcharea":"psych",
                                    "researcharea_color":"#3CDE38"
                                },
                                {
                                    "name":"DEREK D RUCKER",
                                    "gender":"man",
                                    "gender_color":"blue",
                                    "researcharea":"psych",
                                    "researcharea_color":"#3CDE38"
                                },
                                {
                                    "name":"CHRISTOPHER A LOERSCH",
                                    "gender":"man",
                                    "gender_color":"blue",
                                    "researcharea":"psych",
                                    "researcharea_color":"#3CDE38",
                                    "children":[
                                        {
                                            "name":"SHANA R STITES",
                                            "gender":"woman",
                                            "gender_color":"red",
                                            "researcharea":"psych",
                                            "researcharea_color":"#3CDE38"
                                        }
                                    ]
                                },
                                {
                                    "name":"BENJAMIN C WAGNER",
                                    "gender":"man",
                                    "gender_color":"blue",
                                    "researcharea":"psych",
                                    "researcharea_color":"#3CDE38"
                                },
                                {
                                    "name":"NICHOLAS F WRIGHT",
                                    "gender":"man",
                                    "gender_color":"blue",
                                    "researcharea":"psych",
                                    "researcharea_color":"#3CDE38"
                                },
                                {
                                    "name":"CURTIS P HAUGTVEDT",
                                    "gender":"man",
                                    "gender_color":"blue",
                                    "researcharea":"psych",
                                    "researcharea_color":"#3CDE38"
                                },
                                {
                                    "name":"ZAKARY L TORMALA",
                                    "gender":"man",
                                    "gender_color":"blue",
                                    "researcharea":"psych",
                                    "researcharea_color":"#3CDE38"
                                },
                                {
                                    "name":"ANDREW  LUTTRELL",
                                    "gender":"man",
                                    "gender_color":"blue",
                                    "researcharea":"psych",
                                    "researcharea_color":"#3CDE38"
                                },
                                {
                                    "name":"JACOB  TEENY",
                                    "gender":"man",
                                    "gender_color":"blue",
                                    "researcharea":"psych",
                                    "researcharea_color":"#3CDE38"
                                }
                            ]
                        }
                    ]
                }
            ]
        }
    ]
}