{
    "name":"JOHN  LYONS",
    "gender":"man",
    "gender_color":"blue",
    "researcharea":"neuro",
    "researcharea_color":"#F3E09A",
    "children":[
        {
            "name":"SCOTT C LEON",
            "gender":"man",
            "gender_color":"blue",
            "researcharea":"neuro",
            "researcharea_color":"#F3E09A",
            "children":[
                {
                    "name":"BRITTANY L LAKIN",
                    "gender":"woman",
                    "gender_color":"red",
                    "researcharea":"neuro",
                    "researcharea_color":"#F3E09A"
                }
            ]
        }
    ]
}