{
    "name":"RUNE  SIMEONSSON",
    "gender":"man",
    "gender_color":"blue",
    "researcharea":"psych",
    "researcharea_color":"#3CDE38",
    "children":[
        {
            "name":"KRISTIN  THORLEIFSDOTTIR",
            "gender":"woman",
            "gender_color":"red",
            "researcharea":"psych",
            "researcharea_color":"#3CDE38"
        },
        {
            "name":"SHARON LEE CARNAHAN",
            "gender":"woman",
            "gender_color":"red",
            "researcharea":"psych",
            "researcharea_color":"#3CDE38",
            "children":[
                {
                    "name":"HOPE K GERDE",
                    "gender":"woman",
                    "gender_color":"red",
                    "researcharea":"psych",
                    "researcharea_color":"#3CDE38"
                }
            ]
        }
    ]
}