{
    "name":"ANGUS  GELLATLY",
    "gender":"man",
    "gender_color":"blue",
    "researcharea":"psych",
    "researcharea_color":"#3CDE38",
    "children":[
        {
            "name":"GEOFF  COLE",
            "gender":"man",
            "gender_color":"blue",
            "researcharea":"psych",
            "researcharea_color":"#3CDE38",
            "children":[
                {
                    "name":"GUSTAV  KUHN",
                    "gender":"man",
                    "gender_color":"blue",
                    "researcharea":"psych",
                    "researcharea_color":"#3CDE38"
                }
            ]
        }
    ]
}